{
  "objectInfo" : {
    "id" : "0fMiZ9elEFWbkySB7811mC",
    "name" : " zee_OracleStopOnError_MCT",
    "type" : "MTT",
    "metadata" : {
      "modelVersion" : {
        "major" : 0,
        "minor" : 0
      },
      "repoInfo" : {
        "repoHandle" : "001P820Z0000000000HD"
      },
      "contextAttributes" : [ {
        "name" : "id",
        "value" : "@1"
      } ],
      "additionalInfo" : {
        "description" : "",
        "contentType" : null,
        "documentState" : "VALID"
      }
    }
  },
  "dataFileExtension" : "zip",
  "objectRefs" : [ {
    "id" : "0c9wNG5YNYnbF6Kl3SDuir",
    "name" : "zeeshan_Windows",
    "type" : "AgentGroup",
    "metadata" : {
      "modelVersion" : {
        "major" : 0,
        "minor" : 0
      },
      "repoInfo" : {
        "repoHandle" : "001P822500000000000H"
      },
      "contextAttributes" : null,
      "additionalInfo" : {
        "description" : null,
        "contentType" : "JSON",
        "documentState" : "VALID"
      }
    },
    "path" : "/SYS"
  }, {
    "id" : "4U0ZtAxnJSBh36kTadC5Cj",
    "name" : "Xflat_files_vm_2",
    "type" : "Connection",
    "metadata" : {
      "modelVersion" : {
        "major" : 0,
        "minor" : 0
      },
      "repoInfo" : {
        "repoHandle" : "001P820B000000000069"
      },
      "contextAttributes" : null,
      "additionalInfo" : {
        "description" : null,
        "contentType" : "JSON",
        "documentState" : "VALID"
      }
    },
    "path" : "/SYS"
  }, {
    "id" : "gTICCmfOaIsiyJyZOpcTos",
    "name" : "zh_Oracle",
    "type" : "Connection",
    "metadata" : {
      "modelVersion" : {
        "major" : 0,
        "minor" : 0
      },
      "repoInfo" : {
        "repoHandle" : "001P820B00000000000N"
      },
      "contextAttributes" : null,
      "additionalInfo" : {
        "description" : null,
        "contentType" : "JSON",
        "documentState" : "VALID"
      }
    },
    "path" : "/SYS"
  }, {
    "id" : "h8vZ3MKgagEkJNO5Wh0Fg6",
    "name" : "zee_OracleStopOnError",
    "type" : "DTEMPLATE",
    "metadata" : {
      "modelVersion" : {
        "major" : 0,
        "minor" : 0
      },
      "repoInfo" : {
        "repoHandle" : "001P82170000000000A9"
      },
      "contextAttributes" : null,
      "additionalInfo" : {
        "description" : "",
        "contentType" : "JSON",
        "documentState" : "VALID"
      }
    },
    "path" : "/Explore/Default"
  } ]
}